malva_client/__init__.py
malva_client-0.0.1.dist-info/METADATA
malva_client-0.0.1.dist-info/WHEEL
malva_client-0.0.1.dist-info/top_level.txt
malva_client-0.0.1.dist-info/RECORD
