Metadata-Version: 2.4
Name: malva-client
Version: 0.0.1
Summary: Malva Client for the Malva Index
Home-page: https://github.com/malva-bio/malva-client
Author: Daniel León-Periñán
Author-email: Daniel León-Periñán <daniel.leonperinan@mdc-berlin.de>
License: MIT
Classifier: Development Status :: 1 - Planning
Classifier: Intended Audience :: Developers
Classifier: License :: OSI Approved :: MIT License
Classifier: Operating System :: OS Independent
Classifier: Programming Language :: Python :: 3
Requires-Python: >=3.7
Dynamic: author
Dynamic: home-page
Dynamic: requires-python
